.gitignore
.travis.yml
LICENSE.txt
MANIFEST.in
README.md
setup.cfg
setup.py
tox.ini
src/drf_json_api_utils/__init__.py
src/drf_json_api_utils/common.py
src/drf_json_api_utils/constructors.py
src/drf_json_api_utils/factory.py
src/drf_json_api_utils/generic_relation.py
src/drf_json_api_utils/json_api_spec_http_methods.py
src/drf_json_api_utils/lookups.py
src/drf_json_api_utils/namespace.py
src/drf_json_api_utils/plugins.py
src/drf_json_api_utils/types.py
src/drf_json_api_utils.egg-info/PKG-INFO
src/drf_json_api_utils.egg-info/SOURCES.txt
src/drf_json_api_utils.egg-info/dependency_links.txt
src/drf_json_api_utils.egg-info/requires.txt
src/drf_json_api_utils.egg-info/top_level.txt
src/drf_json_api_utils/sql_alchemy/__init__.py
src/drf_json_api_utils/sql_alchemy/constructors.py
src/drf_json_api_utils/sql_alchemy/factory.py
src/drf_json_api_utils/sql_alchemy/namespace.py
src/drf_json_api_utils/sql_alchemy/types.py
tests/__init__.py
tests/test_simple.py